aiomesh/__init__.py
aiomesh/__version__.py
aiomesh/abc.py
aiomesh-0.1.0a1.dist-info/METADATA
aiomesh-0.1.0a1.dist-info/WHEEL
aiomesh-0.1.0a1.dist-info/RECORD
