Metadata-Version: 2.4
Name: aiomesh
Version: 0.1.0a1
Summary: Async Python queue-based operator mesh.
License: MIT
Requires-Python: >=3.8
